chatango/__init__.py
chatango/client.py
chatango/exceptions.py
chatango/handler.py
chatango/hasher.py
chatango/message.py
chatango/pm.py
chatango/room.py
chatango/user.py
chatango/utils.py
chatango_lib-1.5.4.dist-info/LICENSE
chatango_lib-1.5.4.dist-info/METADATA
chatango_lib-1.5.4.dist-info/WHEEL
chatango_lib-1.5.4.dist-info/RECORD
