Metadata-Version: 2.1
Name: chatango-lib
Version: 1.5.4
Summary: Chatango bot library using asyncio
License: GPL-3.0-or-later
Author: LmaoLover
Author-email: hello@lmao.love
Requires-Python: >=3.8,<4.0
Classifier: License :: OSI Approved :: GNU General Public License v3 or later (GPLv3+)
Classifier: Programming Language :: Python :: 3
Classifier: Programming Language :: Python :: 3.8
Classifier: Programming Language :: Python :: 3.9
Classifier: Programming Language :: Python :: 3.10
Classifier: Programming Language :: Python :: 3.11
Requires-Dist: aiohttp (>=3.8.6,<4.0.0)
